odoo8_addon_l10n_es_fiscal_year_closing-8.0.2.0.0-py2.7-nspkg.pth
odoo8_addon_l10n_es_fiscal_year_closing-8.0.2.0.0.dist-info/DESCRIPTION.rst
odoo8_addon_l10n_es_fiscal_year_closing-8.0.2.0.0.dist-info/METADATA
odoo8_addon_l10n_es_fiscal_year_closing-8.0.2.0.0.dist-info/RECORD
odoo8_addon_l10n_es_fiscal_year_closing-8.0.2.0.0.dist-info/WHEEL
odoo8_addon_l10n_es_fiscal_year_closing-8.0.2.0.0.dist-info/metadata.json
odoo8_addon_l10n_es_fiscal_year_closing-8.0.2.0.0.dist-info/namespace_packages.txt
odoo8_addon_l10n_es_fiscal_year_closing-8.0.2.0.0.dist-info/top_level.txt
odoo_addons/l10n_es_fiscal_year_closing/__init__.py
odoo_addons/l10n_es_fiscal_year_closing/__openerp__.py
odoo_addons/l10n_es_fiscal_year_closing/i18n/bg.po
odoo_addons/l10n_es_fiscal_year_closing/i18n/ca.po
odoo_addons/l10n_es_fiscal_year_closing/i18n/ca_ES.po
odoo_addons/l10n_es_fiscal_year_closing/i18n/cs.po
odoo_addons/l10n_es_fiscal_year_closing/i18n/es.po
odoo_addons/l10n_es_fiscal_year_closing/i18n/es_CO.po
odoo_addons/l10n_es_fiscal_year_closing/i18n/es_CR.po
odoo_addons/l10n_es_fiscal_year_closing/i18n/eu.po
odoo_addons/l10n_es_fiscal_year_closing/i18n/fr.po
odoo_addons/l10n_es_fiscal_year_closing/i18n/gl.po
odoo_addons/l10n_es_fiscal_year_closing/i18n/hr.po
odoo_addons/l10n_es_fiscal_year_closing/i18n/l10n_es_fiscal_year_closing.pot
odoo_addons/l10n_es_fiscal_year_closing/i18n/nl.po
odoo_addons/l10n_es_fiscal_year_closing/i18n/pl.po
odoo_addons/l10n_es_fiscal_year_closing/i18n/pt.po
odoo_addons/l10n_es_fiscal_year_closing/i18n/pt_BR.po
odoo_addons/l10n_es_fiscal_year_closing/i18n/ru.po
odoo_addons/l10n_es_fiscal_year_closing/i18n/sl.po
odoo_addons/l10n_es_fiscal_year_closing/i18n/sv.po
odoo_addons/l10n_es_fiscal_year_closing/i18n/tr.po
odoo_addons/l10n_es_fiscal_year_closing/i18n/vi.po
odoo_addons/l10n_es_fiscal_year_closing/images/l10n_es_fiscal_year_closing.png
odoo_addons/l10n_es_fiscal_year_closing/models/__init__.py
odoo_addons/l10n_es_fiscal_year_closing/models/account_fiscalyear.py
odoo_addons/l10n_es_fiscal_year_closing/models/fiscalyear_closing.py
odoo_addons/l10n_es_fiscal_year_closing/models/l10n_es_fiscalyear_closing.py
odoo_addons/l10n_es_fiscal_year_closing/security/ir.model.access.csv
odoo_addons/l10n_es_fiscal_year_closing/security/security.xml
odoo_addons/l10n_es_fiscal_year_closing/static/description/calendar_file.svg
odoo_addons/l10n_es_fiscal_year_closing/static/description/icon.png
