Metadata-Version: 2.0
Name: odoo8-addon-l10n-es-fiscal-year-closing
Version: 8.0.2.0.0
Summary: Cierre de ejercicio fiscal para España
Home-page: http://www.pexego.es
Author: Pexego,Odoo Community Association (OCA)
Author-email: support@odoo-community.org
License: AGPL-3
Platform: UNKNOWN
Classifier: Programming Language :: Python :: 2.7
Classifier: Framework :: Odoo
Classifier: License :: OSI Approved :: GNU Affero General Public License v3
Requires-Dist: odoo (<9.0a,>=8.0a)
